aiohandler/__init__.py
aiohandler/aiohandler.py
aiohandler-0.1.0.dist-info/LICENSE
aiohandler-0.1.0.dist-info/METADATA
aiohandler-0.1.0.dist-info/WHEEL
aiohandler-0.1.0.dist-info/top_level.txt
aiohandler-0.1.0.dist-info/RECORD
