Metadata-Version: 2.1
Name: aiohandler
Version: 0.1.0
Summary: httpheader for logging on async
Home-page: https://github.com/grarich123/aiohandler
Author: grarich
Author-email: grarich123+github@gmail.com
License: UNKNOWN
Platform: UNKNOWN
Classifier: Programming Language :: Python :: 3.8
Classifier: License :: OSI Approved :: MIT License
Classifier: Operating System :: OS Independent
